[{"model": "locations.location", "pk": 1, "fields": {"region": "", "country": "Spain", "created_at": "2017-08-30T00:55:22.936Z", "updated_at": "2017-08-30T00:55:22.936Z"}}, {"model": "locations.location", "pk": 2, "fields": {"region": "Burgundy", "country": "France", "created_at": "2017-08-30T00:57:05.170Z", "updated_at": "2017-08-30T00:57:05.170Z"}}, {"model": "locations.location", "pk": 3, "fields": {"region": "Champagne", "country": "France", "created_at": "2017-08-30T00:57:17.777Z", "updated_at": "2017-08-30T00:57:17.777Z"}}, {"model": "locations.location", "pk": 4, "fields": {"region": "California", "country": "US", "created_at": "2017-08-30T00:57:47.794Z", "updated_at": "2017-08-30T00:57:47.794Z"}}, {"model": "locations.location", "pk": 5, "fields": {"region": "", "country": "Australia", "created_at": "2017-08-30T00:58:00.642Z", "updated_at": "2017-08-30T00:58:00.642Z"}}, {"model": "locations.location", "pk": 6, "fields": {"region": "Loire Valley", "country": "France", "created_at": "2017-08-30T01:00:11.069Z", "updated_at": "2017-08-30T01:00:11.069Z"}}, {"model": "locations.location", "pk": 7, "fields": {"region": "", "country": "Austria", "created_at": "2017-08-30T01:01:35.301Z", "updated_at": "2017-08-30T01:01:35.301Z"}}, {"model": "locations.location", "pk": 8, "fields": {"region": "", "country": "Italy", "created_at": "2017-08-30T01:02:48.522Z", "updated_at": "2017-08-30T01:02:48.522Z"}}, {"model": "locations.location", "pk": 9, "fields": {"region": "Oregon", "country": "US", "created_at": "2017-08-30T01:02:57.823Z", "updated_at": "2017-08-30T01:02:57.823Z"}}, {"model": "locations.location", "pk": 10, "fields": {"region": "", "country": "Germany", "created_at": "2017-08-30T01:05:36.538Z", "updated_at": "2017-08-30T01:05:36.538Z"}}, {"model": "locations.location", "pk": 11, "fields": {"region": "Alsace", "country": "France", "created_at": "2017-08-30T01:05:50.481Z", "updated_at": "2017-08-30T01:05:50.481Z"}}, {"model": "locations.location", "pk": 12, "fields": {"region": "New York State", "country": "US", "created_at": "2017-08-30T01:06:07.480Z", "updated_at": "2017-08-30T01:06:37.317Z"}}, {"model": "locations.location", "pk": 13, "fields": {"region": "Washington State", "country": "US", "created_at": "2017-08-30T01:06:20.595Z", "updated_at": "2017-08-30T01:06:20.595Z"}}, {"model": "locations.location", "pk": 14, "fields": {"region": "Bordeaux", "country": "France", "created_at": "2017-08-30T01:07:12.648Z", "updated_at": "2017-08-30T01:07:12.648Z"}}, {"model": "locations.location", "pk": 15, "fields": {"region": "", "country": "New Zealand", "created_at": "2017-08-30T01:07:27.263Z", "updated_at": "2017-08-30T01:07:27.263Z"}}, {"model": "locations.location", "pk": 16, "fields": {"region": "Rhone Valley", "country": "France", "created_at": "2017-08-30T01:09:43.792Z", "updated_at": "2017-08-30T01:09:43.792Z"}}, {"model": "locations.location", "pk": 17, "fields": {"region": "Beaujolais", "country": "France", "created_at": "2017-08-30T01:11:14.356Z", "updated_at": "2017-08-30T01:11:14.356Z"}}, {"model": "locations.location", "pk": 18, "fields": {"region": "Rioja", "country": "Spain", "created_at": "2017-08-30T01:13:25.244Z", "updated_at": "2017-08-30T01:13:25.244Z"}}, {"model": "locations.location", "pk": 19, "fields": {"region": "Tuscany", "country": "Italy", "created_at": "2017-08-30T01:14:19.067Z", "updated_at": "2017-08-30T01:14:19.067Z"}}, {"model": "locations.location", "pk": 20, "fields": {"region": "Napa Valley", "country": "US", "created_at": "2017-08-30T01:15:40.858Z", "updated_at": "2017-08-30T01:15:40.858Z"}}, {"model": "locations.location", "pk": 21, "fields": {"region": "", "country": "Chile", "created_at": "2017-08-30T01:16:52.682Z", "updated_at": "2017-08-30T01:16:52.682Z"}}, {"model": "locations.location", "pk": 22, "fields": {"region": "Piedmont", "country": "Italy", "created_at": "2017-08-30T01:17:49.728Z", "updated_at": "2017-08-30T01:17:49.728Z"}}, {"model": "locations.location", "pk": 23, "fields": {"region": "Cahor", "country": "France", "created_at": "2017-08-30T01:23:57.472Z", "updated_at": "2017-08-30T01:23:57.472Z"}}, {"model": "locations.location", "pk": 24, "fields": {"region": "", "country": "Argentina", "created_at": "2017-08-30T01:24:06.293Z", "updated_at": "2017-08-30T01:24:06.293Z"}}]